baycomp_plotting/__init__.py
baycomp_plotting/plotting.py
baycomp_plotting-1.1.dist-info/LICENSE
baycomp_plotting-1.1.dist-info/METADATA
baycomp_plotting-1.1.dist-info/WHEEL
baycomp_plotting-1.1.dist-info/top_level.txt
baycomp_plotting-1.1.dist-info/RECORD
