Metadata-Version: 2.1
Name: baycomp-plotting
Version: 1.1
Summary: This package provides some extra functionality for plotting baycomp's posteriors.
Home-page: https://github.com/mjuez/baycomp_plotting
Author: Mario Juez-Gil
Author-email: mariojg@ubu.es
License: GPLv3
Download-URL: https://github.com/mjuez/baycomp_plotting/archive/v1_1.tar.gz
Platform: UNKNOWN
Classifier: Development Status :: 5 - Production/Stable
Classifier: Intended Audience :: Science/Research
Classifier: Topic :: Scientific/Engineering
Classifier: License :: OSI Approved :: GNU General Public License v3 (GPLv3)
Classifier: Programming Language :: Python :: 3
Classifier: Programming Language :: Python :: 3.6
Classifier: Programming Language :: Python :: 3.7
Classifier: Programming Language :: Python :: 3.8
Requires-Dist: matplotlib (==3.3.2)
Requires-Dist: numpy (==1.19.1)
Requires-Dist: iteround (==1.0.2)
Requires-Dist: scipy (==1.5.3)
